{
  "intents": [
    {
      "intent": "GetNextArrivalsByStopNumberIntent",
      "slots": [
        {
          "name": "busStop",
          "type": "NUMBER"
        }
      ]
    },
    {
      "intent": "SaveStopShortcutIntent",
      "slots": [
        {
          "name": "busStop",
          "type": "NUMBER"
        },
        {
          "name": "stopDirection",
          "type": "DIRECTION"          
        }
      ]
    },
    {
      "intent": "ConfirmSaveIntent",
      "slots": [
      ]
    },
    {
      "intent": "CancelSaveIntent",
      "slots": [
      ]
    },
    {
      "intent": "GetNextArrivalsBySavedStopIntent",
      "slots": [
        {
          "name": "stopDirection",
          "type": "DIRECTION"
        },
        {
          "name": "routeName",
          "type": "LITERAL"            
        }
      ]
    },
    {
      "intent": "AMAZON.HelpIntent"
    },
    {
      "intent": "AMAZON.StopIntent"
    }
  ]
}
